salt_tempo_relay.py
salt_tempo_relay-0.0.4.dist-info/METADATA
salt_tempo_relay-0.0.4.dist-info/WHEEL
salt_tempo_relay-0.0.4.dist-info/entry_points.txt
salt_tempo_relay-0.0.4.dist-info/top_level.txt
salt_tempo_relay-0.0.4.dist-info/RECORD
